peaceful_pie/__init__.py
peaceful_pie/py.typed
peaceful_pie/ray_results_helper.py
peaceful_pie/unity_comms.py
peaceful_pie-2.0.0.dist-info/WHEEL
peaceful_pie-2.0.0.dist-info/METADATA
peaceful_pie-2.0.0.dist-info/LICENSE
peaceful_pie-2.0.0.dist-info/RECORD
