Metadata-Version: 2.1
Name: peaceful-pie
Version: 2.0.0
Summary: Control Unity from Python!
Home-page: https://github.com/hughperkins/peaceful-pie
License: MIT
Author: Hugh Perkins
Author-email: hughperkins@gmail.com
Requires-Python: >=3.10,<4.0
Classifier: License :: OSI Approved :: MIT License
Classifier: Programming Language :: Python :: 3
Classifier: Programming Language :: Python :: 3.10
Classifier: Programming Language :: Python :: 3.11
Requires-Dist: chili (>=1.8.0,<2.0.0)
Requires-Dist: numpy (>=1.24.1,<2.0.0)
Requires-Dist: requests (>=2.28.1,<3.0.0)
Project-URL: Repository, https://github.com/hughperkins/peaceful-pie
